biosynonyms/__init__.py
biosynonyms/generate_owl.py
biosynonyms/lint.py
biosynonyms/model.py
biosynonyms/predict.py
biosynonyms/py.typed
biosynonyms/version.py
biosynonyms/resources/__init__.py
biosynonyms/resources/negatives.tsv
biosynonyms/resources/positives.tsv
biosynonyms/resources/unentities.tsv
biosynonyms-0.3.3.dist-info/LICENSE
biosynonyms-0.3.3.dist-info/LICENSE-MIT
biosynonyms-0.3.3.dist-info/METADATA
biosynonyms-0.3.3.dist-info/WHEEL
biosynonyms-0.3.3.dist-info/top_level.txt
biosynonyms-0.3.3.dist-info/RECORD
