Metadata-Version: 2.2
Name: biosynonyms
Version: 0.3.3
Summary: Decentralized database of biomedical synonyms
Author-email: Charles Tapley Hoyt <cthoyt@gmail.com>
Maintainer-email: Charles Tapley Hoyt <cthoyt@gmail.com>
License: Creative Commons Legal Code
Project-URL: Bug Tracker, https://github.com/biopragmatics/biosynonyms/issues
Project-URL: Homepage, https://github.com/biopragmatics/biosynonyms
Project-URL: Repository, https://github.com/biopragmatics/biosynonyms.git
Project-URL: Documentation, https://biosynonyms.readthedocs.io
Keywords: snekpack,cookiecutter,databases,biological databases,biomedical databases,natural language processing,NLP,ontologies,biomedical ontologies
Classifier: Development Status :: 4 - Beta
Classifier: Environment :: Console
Classifier: Intended Audience :: Developers
Classifier: License :: OSI Approved :: MIT License
Classifier: Operating System :: OS Independent
Classifier: Framework :: Pytest
Classifier: Framework :: tox
Classifier: Framework :: Sphinx
Classifier: Programming Language :: Python
Classifier: Programming Language :: Python :: 3.10
Classifier: Programming Language :: Python :: 3.11
Classifier: Programming Language :: Python :: 3.12
Classifier: Programming Language :: Python :: 3 :: Only
Classifier: Framework :: Pydantic
Classifier: Framework :: Pydantic :: 2
Requires-Python: >=3.10
License-File: LICENSE
License-File: LICENSE-MIT
Requires-Dist: click
Requires-Dist: tqdm
Requires-Dist: curies>=0.10.4
Requires-Dist: bioregistry
Requires-Dist: pydantic>=2.0
Requires-Dist: pydantic_extra_types
Requires-Dist: pycountry
Requires-Dist: typing_extensions
Provides-Extra: tests
Requires-Dist: pytest; extra == "tests"
Requires-Dist: coverage; extra == "tests"
Requires-Dist: gilda; extra == "tests"
Requires-Dist: pandas; extra == "tests"
Provides-Extra: docs
Requires-Dist: sphinx>=8; extra == "docs"
Requires-Dist: sphinx-rtd-theme>=3.0; extra == "docs"
Requires-Dist: sphinx_automodapi; extra == "docs"
Provides-Extra: numbers
Requires-Dist: numbers-parser; extra == "numbers"
Provides-Extra: predict
Requires-Dist: indra; extra == "predict"
Requires-Dist: gilda; extra == "predict"
Requires-Dist: embiggen; extra == "predict"
Requires-Dist: ensmallen; extra == "predict"
Requires-Dist: matplotlib; extra == "predict"
Requires-Dist: seaborn; extra == "predict"
Requires-Dist: pyarrow; extra == "predict"
Requires-Dist: fastparquet; extra == "predict"
Requires-Dist: pandas; extra == "predict"
Requires-Dist: more_click; extra == "predict"
